migrations/__init__.py
models/__init__.py
models/seo_page.py
seo/__init__.py
seo/apps.py
seo/urls.py
seo/views.py
seo/wagtail_hooks.py
seo/migrations/__init__.py
seo/models/__init__.py
seo/models/seo_page.py
seo/static/__init__.py
seo/static/css/__init__.py
seo/static/css/seo.css
seo/static/images/__init__.py
seo/static/images/seo_logo.png
seo/static/js/__init__.py
seo/static/js/helper.js
seo/static/js/seoSidePannel.js
seo/testing/__init__.py
seo/testing/test_api.py
checklist_seo-0.0.7.dist-info/LICENSE
checklist_seo-0.0.7.dist-info/METADATA
checklist_seo-0.0.7.dist-info/WHEEL
checklist_seo-0.0.7.dist-info/top_level.txt
checklist_seo-0.0.7.dist-info/RECORD
