Metadata-Version: 2.1
Name: checklist-seo
Version: 0.0.7
Summary: The full checklist to provide tools inside Django in order to write right content
Home-page: https://github.com/itarverne/checklist-seo
Author: RIGAUDIE David
License: MIT
Platform: any
Classifier: Development Status :: 4 - Beta
Classifier: Environment :: Web Environment
Classifier: Intended Audience :: Developers
Classifier: License :: OSI Approved :: MIT License
Classifier: Operating System :: OS Independent
Classifier: Programming Language :: Python
Classifier: Programming Language :: Python :: 3
Classifier: Topic :: Software Development :: Libraries :: Python Modules
Classifier: Framework :: Django :: 3.1
Requires-Python: >=3.7
Requires-Dist: Django (<3.2,>=3.1)
Requires-Dist: nltk (>=3.5)
Requires-Dist: lxml (>=4.5.2)
